msaBase/__init__.py
msaBase/config.py
msaBase/configurate.py
msaBase/errorhandling.py
msaBase/helpers.py
msaBase/logger.py
msaBase/models/__init__.py
msaBase/models/functionality.py
msaBase/models/middlewares.py
msaBase/models/settings.py
msaBase/models/sysinfo.py
msaBase/profiler.py
msaBase/sysinfo.py
msaBase/utils/__init__.py
msaBase/utils/constants.py
msabase-0.0.136.dist-info/METADATA
msabase-0.0.136.dist-info/WHEEL
msabase-0.0.136.dist-info/RECORD
