Metadata-Version: 2.1
Name: msaBase
Version: 0.0.136
Summary: General Package for Microservices based on FastAPI like Profiler, Scheduler, Sysinfo, Healtcheck, Error Handling etc.
Author: Stefan Welcker
Requires-Python: >=3.9.0,<3.11
Classifier: Programming Language :: Python :: 3
Classifier: Programming Language :: Python :: 3.9
Classifier: Programming Language :: Python :: 3.10
Requires-Dist: Jinja2 (==3.1.2)
Requires-Dist: Starlette-WTF (==0.4.3)
Requires-Dist: addict (==2.4.0)
Requires-Dist: aiofiles (==23.1.0)
Requires-Dist: aiohttp (==3.8.4)
Requires-Dist: anyio (==3.7.1)
Requires-Dist: apscheduler (==3.10.0)
Requires-Dist: autoflake (==2.0.1)
Requires-Dist: black (==22.6.0)
Requires-Dist: colorama (==0.4.6)
Requires-Dist: confluent-kafka (>=2.3.0,<3.0.0)
Requires-Dist: fastapi[all] (==0.86.0)
Requires-Dist: fastapi_utils (==0.2.1)
Requires-Dist: flake8 (==6.0.0)
Requires-Dist: fs (==2.4.16)
Requires-Dist: gputil (==1.4.0)
Requires-Dist: hjson (==3.1.0)
Requires-Dist: httpx (==0.23.3)
Requires-Dist: isort (==5.12.0)
Requires-Dist: loguru (==0.6.0)
Requires-Dist: lxml (==4.9.2)
Requires-Dist: msaDocModels (==0.0.114)
Requires-Dist: msaFileSystem (==0.0.8)
Requires-Dist: msgpack-asgi (==1.1.0)
Requires-Dist: mypy (==1.0.0)
Requires-Dist: orjson (==3.8.3)
Requires-Dist: prometheus_fastapi_instrumentator (==5.9.1)
Requires-Dist: psutil (==5.9.4)
Requires-Dist: pydantic[dotenv,email] (==1.9.2)
Requires-Dist: pyinstrument (==4.4.0)
Requires-Dist: pymongo (==4.3.3)
Requires-Dist: pyproject-flake8 (==6.0.0)
Requires-Dist: pytest (==7.2.0)
Requires-Dist: pytest-asyncio (==0.20.2)
Requires-Dist: pytest-mock (==3.10.0)
Requires-Dist: sentry-sdk (==1.24.0)
Requires-Dist: setuptools (==67.6.1)
Requires-Dist: slowapi (==0.1.7)
Requires-Dist: starception (==0.4.1)
Requires-Dist: starlette (==0.20.4)
Requires-Dist: starlette-context (==0.3.5)
Requires-Dist: uvicorn (==0.18.3)
Requires-Dist: uvloop (==0.17.0)
